xradio/__init__.py
xradio/_utils/__init__.py
xradio/_utils/coord_math.py
xradio/_utils/dict_helpers.py
xradio/_utils/list_and_array.py
xradio/_utils/schema.py
xradio/_utils/_casacore/casacore_from_casatools.py
xradio/_utils/_casacore/tables.py
xradio/_utils/zarr/__init__.py
xradio/_utils/zarr/common.py
xradio/image/__init__.py
xradio/image/image.py
xradio/image/_util/__init__.py
xradio/image/_util/casacore.py
xradio/image/_util/common.py
xradio/image/_util/image_factory.py
xradio/image/_util/zarr.py
xradio/image/_util/_casacore/__init__.py
xradio/image/_util/_casacore/common.py
xradio/image/_util/_casacore/xds_from_casacore.py
xradio/image/_util/_casacore/xds_to_casacore.py
xradio/image/_util/_fits/xds_from_fits.py
xradio/image/_util/_zarr/common.py
xradio/image/_util/_zarr/xds_from_zarr.py
xradio/image/_util/_zarr/xds_to_zarr.py
xradio/image/_util/_zarr/zarr_low_level.py
xradio/measurement_set/__init__.py
xradio/measurement_set/convert_msv2_to_processing_set.py
xradio/measurement_set/load_processing_set.py
xradio/measurement_set/measurement_set_xdt.py
xradio/measurement_set/open_processing_set.py
xradio/measurement_set/processing_set_xdt.py
xradio/measurement_set/schema.py
xradio/measurement_set/_utils/__init__.py
xradio/measurement_set/_utils/_msv2/__init__.py
xradio/measurement_set/_utils/_msv2/conversion.py
xradio/measurement_set/_utils/_msv2/create_antenna_xds.py
xradio/measurement_set/_utils/_msv2/create_field_and_source_xds.py
xradio/measurement_set/_utils/_msv2/msv2_to_msv4_meta.py
xradio/measurement_set/_utils/_msv2/msv4_info_dicts.py
xradio/measurement_set/_utils/_msv2/msv4_sub_xdss.py
xradio/measurement_set/_utils/_msv2/optimised_functions.py
xradio/measurement_set/_utils/_msv2/partition_queries.py
xradio/measurement_set/_utils/_msv2/subtables.py
xradio/measurement_set/_utils/_msv2/_tables/read.py
xradio/measurement_set/_utils/_msv2/_tables/read_main_table.py
xradio/measurement_set/_utils/_msv2/_tables/table_query.py
xradio-1.0.2.dist-info/licenses/LICENSE.txt
xradio-1.0.2.dist-info/METADATA
xradio-1.0.2.dist-info/WHEEL
xradio-1.0.2.dist-info/top_level.txt
xradio-1.0.2.dist-info/RECORD
