Metadata-Version: 2.4
Name: xradio
Version: 1.0.2
Summary:  Xarray Radio Astronomy Data IO
Author-email: Jan-Willem Steeb <jsteeb@nrao.edu>, Federico Montesino Pouzols <pouzols@eso.edu>, Dave Mehringer <dmehring@nrao.edu>, Peter Wortmann <peter.wortmann@skao.int>
License: BSD 3-Clause License
Requires-Python: <3.14,>=3.11
License-File: LICENSE.txt
Requires-Dist: astropy
Requires-Dist: toolviper>=0.0.12
Requires-Dist: numba>=0.57.0
Requires-Dist: s3fs
Requires-Dist: scipy
Requires-Dist: xarray
Requires-Dist: zarr<3,>=2
Requires-Dist: pyarrow
Requires-Dist: typeguard
Requires-Dist: numcodecs<0.16
Requires-Dist: psutil
Provides-Extra: test
Requires-Dist: pytest; extra == "test"
Requires-Dist: pytest-cov; extra == "test"
Requires-Dist: pytest-html; extra == "test"
Provides-Extra: python-casacore
Requires-Dist: python_casacore>=3.6.1; sys_platform != "darwin" and extra == "python-casacore"
Provides-Extra: interactive
Requires-Dist: matplotlib; extra == "interactive"
Requires-Dist: prettytable; extra == "interactive"
Requires-Dist: jupyterlab; extra == "interactive"
Requires-Dist: ipykernel; extra == "interactive"
Requires-Dist: ipympl; extra == "interactive"
Requires-Dist: ipython; extra == "interactive"
Requires-Dist: jupyter-client; extra == "interactive"
Provides-Extra: docs
Requires-Dist: nbsphinx; extra == "docs"
Requires-Dist: recommonmark; extra == "docs"
Requires-Dist: scanpydoc; extra == "docs"
Requires-Dist: sphinx-autoapi; extra == "docs"
Requires-Dist: sphinx-autosummary-accessors; extra == "docs"
Requires-Dist: sphinx_rtd_theme; extra == "docs"
Requires-Dist: twine; extra == "docs"
Requires-Dist: pandoc; extra == "docs"
Provides-Extra: all
Requires-Dist: pytest; extra == "all"
Requires-Dist: pytest-cov; extra == "all"
Requires-Dist: pytest-html; extra == "all"
Requires-Dist: python_casacore>=3.6.1; sys_platform != "darwin" and extra == "all"
Requires-Dist: matplotlib; extra == "all"
Requires-Dist: prettytable; extra == "all"
Requires-Dist: jupyterlab; extra == "all"
Requires-Dist: ipykernel; extra == "all"
Requires-Dist: ipympl; extra == "all"
Requires-Dist: ipython; extra == "all"
Requires-Dist: jupyter-client; extra == "all"
Requires-Dist: nbsphinx; extra == "all"
Requires-Dist: recommonmark; extra == "all"
Requires-Dist: scanpydoc; extra == "all"
Requires-Dist: sphinx-autoapi; extra == "all"
Requires-Dist: sphinx-autosummary-accessors; extra == "all"
Requires-Dist: sphinx_rtd_theme; extra == "all"
Requires-Dist: twine; extra == "all"
Requires-Dist: pandoc; extra == "all"
Dynamic: license-file
